GridSearchReductor/GridSearchReductor.py
GridSearchReductor/__init__.py
gridsearchreductor-1.0.2.dist-info/licenses/LICENSE
tests/__init__.py
tests/conftest.py
tests/test_grid_search_reductor.py
tests/test_integration.py
gridsearchreductor-1.0.2.dist-info/METADATA
gridsearchreductor-1.0.2.dist-info/WHEEL
gridsearchreductor-1.0.2.dist-info/top_level.txt
gridsearchreductor-1.0.2.dist-info/RECORD
