Metadata-Version: 2.4
Name: GridSearchReductor
Version: 1.0.2
Summary: Reduce hyperparameter search space using stratified sampling (on top of a ParameterGrid)
Home-page: https://github.com/thiswillbeyourgithub/GridSearchReductor.git
Keywords: stratified,sampling,grid-search,optimization,hyperparameter-optimization,machine-learning,experiment-design,parameter-tuning,space-filling,stratified-sampling
Classifier: Programming Language :: Python :: 3
Classifier: Operating System :: OS Independent
Requires-Python: >=3.11
License-File: LICENSE
Requires-Dist: numpy>=1.24.0
Requires-Dist: scikit-learn>=1.3.0
Requires-Dist: joblib
Dynamic: classifier
Dynamic: description
Dynamic: description-content-type
Dynamic: home-page
Dynamic: keywords
Dynamic: license-file
Dynamic: requires-dist
Dynamic: requires-python
Dynamic: summary
